{"training": [{"image": "00000.nii.gz"}, {"image": "00001.nii.gz"}, {"image": "00002.nii.gz"}, {"image": "00003.nii.gz"}, {"image": "00004.nii.gz"}, {"image": "00005.nii.gz"}, {"image": "00006.nii.gz"}, {"image": "00007.nii.gz"}, {"image": "00008.nii.gz"}, {"image": "00009.nii.gz"}, {"image": "00010.nii.gz"}, {"image": "00011.nii.gz"}, {"image": "00012.nii.gz"}, {"image": "00013.nii.gz"}, {"image": "00014.nii.gz"}, {"image": "00015.nii.gz"}, {"image": "00016.nii.gz"}, {"image": "00017.nii.gz"}, {"image": "00018.nii.gz"}, {"image": "00019.nii.gz"}, {"image": "00020.nii.gz"}, {"image": "00021.nii.gz"}, {"image": "00022.nii.gz"}, {"image": "00023.nii.gz"}, {"image": "00024.nii.gz"}, {"image": "00025.nii.gz"}, {"image": "00026.nii.gz"}, {"image": "00027.nii.gz"}, {"image": "00028.nii.gz"}, {"image": "00029.nii.gz"}, {"image": "00030.nii.gz"}, {"image": "00031.nii.gz"}, {"image": "00032.nii.gz"}, {"image": "00033.nii.gz"}, {"image": "00034.nii.gz"}, {"image": "00035.nii.gz"}, {"image": "00036.nii.gz"}, {"image": "00037.nii.gz"}, {"image": "00038.nii.gz"}, {"image": "00039.nii.gz"}, {"image": "00040.nii.gz"}, {"image": "00041.nii.gz"}, {"image": "00042.nii.gz"}, {"image": "00043.nii.gz"}, {"image": "00044.nii.gz"}, {"image": "00045.nii.gz"}, {"image": "00046.nii.gz"}, {"image": "00047.nii.gz"}, {"image": "00048.nii.gz"}, {"image": "00049.nii.gz"}, {"image": "00050.nii.gz"}, {"image": "00051.nii.gz"}, {"image": "00052.nii.gz"}, {"image": "00053.nii.gz"}, {"image": "00054.nii.gz"}, {"image": "00055.nii.gz"}, {"image": "00056.nii.gz"}, {"image": "00057.nii.gz"}, {"image": "00058.nii.gz"}, {"image": "00059.nii.gz"}, {"image": "00060.nii.gz"}, {"image": "00061.nii.gz"}, {"image": "00062.nii.gz"}, {"image": "00063.nii.gz"}, {"image": "00064.nii.gz"}, {"image": "00065.nii.gz"}, {"image": "00066.nii.gz"}, {"image": "00067.nii.gz"}, {"image": "00068.nii.gz"}, {"image": "00069.nii.gz"}, {"image": "00070.nii.gz"}, {"image": "00071.nii.gz"}, {"image": "00072.nii.gz"}, {"image": "00073.nii.gz"}, {"image": "00074.nii.gz"}, {"image": "00075.nii.gz"}, {"image": "00076.nii.gz"}, {"image": "00077.nii.gz"}, {"image": "00078.nii.gz"}, {"image": "00079.nii.gz"}, {"image": "00080.nii.gz"}, {"image": "00081.nii.gz"}, {"image": "00082.nii.gz"}, {"image": "00083.nii.gz"}, {"image": "00084.nii.gz"}, {"image": "00085.nii.gz"}, {"image": "00086.nii.gz"}, {"image": "00087.nii.gz"}, {"image": "00088.nii.gz"}, {"image": "00089.nii.gz"}, {"image": "00090.nii.gz"}, {"image": "00091.nii.gz"}, {"image": "00092.nii.gz"}, {"image": "00093.nii.gz"}, {"image": "00094.nii.gz"}, {"image": "00095.nii.gz"}, {"image": "00096.nii.gz"}, {"image": "00097.nii.gz"}, {"image": "00098.nii.gz"}, {"image": "00099.nii.gz"}, {"image": "00100.nii.gz"}, {"image": "00101.nii.gz"}, {"image": "00102.nii.gz"}, {"image": "00103.nii.gz"}, {"image": "00104.nii.gz"}, {"image": "00105.nii.gz"}, {"image": "00106.nii.gz"}, {"image": "00107.nii.gz"}, {"image": "00108.nii.gz"}, {"image": "00109.nii.gz"}, {"image": "00110.nii.gz"}, {"image": "00111.nii.gz"}, {"image": "00112.nii.gz"}, {"image": "00113.nii.gz"}, {"image": "00114.nii.gz"}, {"image": "00115.nii.gz"}, {"image": "00116.nii.gz"}, {"image": "00117.nii.gz"}, {"image": "00118.nii.gz"}, {"image": "00119.nii.gz"}, {"image": "00120.nii.gz"}, {"image": "00121.nii.gz"}, {"image": "00122.nii.gz"}, {"image": "00123.nii.gz"}, {"image": "00124.nii.gz"}, {"image": "00125.nii.gz"}, {"image": "00126.nii.gz"}, {"image": "00127.nii.gz"}, {"image": "00128.nii.gz"}, {"image": "00129.nii.gz"}, {"image": "00130.nii.gz"}, {"image": "00131.nii.gz"}, {"image": "00132.nii.gz"}, {"image": "00133.nii.gz"}, {"image": "00134.nii.gz"}, {"image": "00135.nii.gz"}, {"image": "00136.nii.gz"}, {"image": "00137.nii.gz"}, {"image": "00138.nii.gz"}, {"image": "00139.nii.gz"}, {"image": "00140.nii.gz"}, {"image": "00141.nii.gz"}, {"image": "00142.nii.gz"}, {"image": "00143.nii.gz"}, {"image": "00144.nii.gz"}, {"image": "00145.nii.gz"}, {"image": "00146.nii.gz"}, {"image": "00147.nii.gz"}, {"image": "00148.nii.gz"}, {"image": "00149.nii.gz"}, {"image": "00150.nii.gz"}, {"image": "00151.nii.gz"}, {"image": "00152.nii.gz"}, {"image": "00153.nii.gz"}, {"image": "00154.nii.gz"}, {"image": "00155.nii.gz"}, {"image": "00156.nii.gz"}, {"image": "00157.nii.gz"}, {"image": "00158.nii.gz"}, {"image": "00159.nii.gz"}, {"image": "00160.nii.gz"}, {"image": "00161.nii.gz"}, {"image": "00162.nii.gz"}, {"image": "00163.nii.gz"}, {"image": "00164.nii.gz"}, {"image": "00165.nii.gz"}, {"image": "00166.nii.gz"}, {"image": "00167.nii.gz"}, {"image": "00168.nii.gz"}, {"image": "00169.nii.gz"}, {"image": "00170.nii.gz"}, {"image": "00171.nii.gz"}, {"image": "00172.nii.gz"}, {"image": "00173.nii.gz"}, {"image": "00174.nii.gz"}, {"image": "00175.nii.gz"}, {"image": "00176.nii.gz"}, {"image": "00177.nii.gz"}, {"image": "00178.nii.gz"}, {"image": "00179.nii.gz"}, {"image": "00180.nii.gz"}, {"image": "00181.nii.gz"}, {"image": "00182.nii.gz"}, {"image": "00183.nii.gz"}, {"image": "00184.nii.gz"}, {"image": "00185.nii.gz"}, {"image": "00186.nii.gz"}, {"image": "00187.nii.gz"}, {"image": "00188.nii.gz"}, {"image": "00189.nii.gz"}, {"image": "00190.nii.gz"}, {"image": "00191.nii.gz"}, {"image": "00192.nii.gz"}, {"image": "00193.nii.gz"}, {"image": "00194.nii.gz"}, {"image": "00195.nii.gz"}, {"image": "00196.nii.gz"}, {"image": "00197.nii.gz"}, {"image": "00198.nii.gz"}, {"image": "00199.nii.gz"}, {"image": "00200.nii.gz"}, {"image": "00201.nii.gz"}, {"image": "00202.nii.gz"}, {"image": "00203.nii.gz"}, {"image": "00204.nii.gz"}, {"image": "00205.nii.gz"}, {"image": "00206.nii.gz"}, {"image": "00207.nii.gz"}, {"image": "00208.nii.gz"}, {"image": "00209.nii.gz"}, {"image": "00210.nii.gz"}, {"image": "00211.nii.gz"}, {"image": "00212.nii.gz"}, {"image": "00213.nii.gz"}, {"image": "00214.nii.gz"}, {"image": "00215.nii.gz"}, {"image": "00216.nii.gz"}, {"image": "00217.nii.gz"}, {"image": "00218.nii.gz"}, {"image": "00219.nii.gz"}, {"image": "00220.nii.gz"}, {"image": "00221.nii.gz"}, {"image": "00222.nii.gz"}, {"image": "00223.nii.gz"}, {"image": "00224.nii.gz"}, {"image": "00225.nii.gz"}, {"image": "00226.nii.gz"}, {"image": "00227.nii.gz"}, {"image": "00228.nii.gz"}, {"image": "00229.nii.gz"}, {"image": "00230.nii.gz"}, {"image": "00231.nii.gz"}, {"image": "00232.nii.gz"}, {"image": "00233.nii.gz"}, {"image": "00234.nii.gz"}, {"image": "00235.nii.gz"}, {"image": "00236.nii.gz"}, {"image": "00237.nii.gz"}, {"image": "00238.nii.gz"}, {"image": "00239.nii.gz"}, {"image": "00240.nii.gz"}, {"image": "00241.nii.gz"}, {"image": "00242.nii.gz"}, {"image": "00243.nii.gz"}, {"image": "00244.nii.gz"}, {"image": "00245.nii.gz"}, {"image": "00246.nii.gz"}, {"image": "00247.nii.gz"}, {"image": "00248.nii.gz"}, {"image": "00249.nii.gz"}, {"image": "00250.nii.gz"}, {"image": "00251.nii.gz"}, {"image": "00252.nii.gz"}, {"image": "00253.nii.gz"}, {"image": "00254.nii.gz"}, {"image": "00255.nii.gz"}, {"image": "00256.nii.gz"}, {"image": "00257.nii.gz"}, {"image": "00258.nii.gz"}, {"image": "00259.nii.gz"}, {"image": "00260.nii.gz"}, {"image": "00261.nii.gz"}, {"image": "00262.nii.gz"}, {"image": "00263.nii.gz"}, {"image": "00264.nii.gz"}, {"image": "00265.nii.gz"}, {"image": "00266.nii.gz"}, {"image": "00267.nii.gz"}, {"image": "00268.nii.gz"}, {"image": "00269.nii.gz"}, {"image": "00270.nii.gz"}, {"image": "00271.nii.gz"}, {"image": "00272.nii.gz"}, {"image": "00273.nii.gz"}, {"image": "00274.nii.gz"}, {"image": "00275.nii.gz"}, {"image": "00276.nii.gz"}, {"image": "00277.nii.gz"}, {"image": "00278.nii.gz"}, {"image": "00279.nii.gz"}, {"image": "00280.nii.gz"}, {"image": "00281.nii.gz"}, {"image": "00282.nii.gz"}, {"image": "00283.nii.gz"}, {"image": "00284.nii.gz"}, {"image": "00285.nii.gz"}, {"image": "00286.nii.gz"}, {"image": "00287.nii.gz"}, {"image": "00288.nii.gz"}, {"image": "00289.nii.gz"}, {"image": "00290.nii.gz"}, {"image": "00291.nii.gz"}, {"image": "00292.nii.gz"}, {"image": "00293.nii.gz"}, {"image": "00294.nii.gz"}, {"image": "00295.nii.gz"}, {"image": "00296.nii.gz"}, {"image": "00297.nii.gz"}, {"image": "00298.nii.gz"}, {"image": "00299.nii.gz"}, {"image": "00300.nii.gz"}, {"image": "00301.nii.gz"}, {"image": "00302.nii.gz"}, {"image": "00303.nii.gz"}, {"image": "00304.nii.gz"}, {"image": "00305.nii.gz"}, {"image": "00306.nii.gz"}, {"image": "00307.nii.gz"}, {"image": "00308.nii.gz"}, {"image": "00309.nii.gz"}, {"image": "00310.nii.gz"}, {"image": "00311.nii.gz"}, {"image": "00312.nii.gz"}, {"image": "00313.nii.gz"}, {"image": "00314.nii.gz"}, {"image": "00315.nii.gz"}, {"image": "00316.nii.gz"}, {"image": "00317.nii.gz"}, {"image": "00318.nii.gz"}, {"image": "00319.nii.gz"}, {"image": "00320.nii.gz"}, {"image": "00321.nii.gz"}, {"image": "00322.nii.gz"}, {"image": "00323.nii.gz"}, {"image": "00324.nii.gz"}, {"image": "00325.nii.gz"}, {"image": "00326.nii.gz"}, {"image": "00327.nii.gz"}, {"image": "00328.nii.gz"}, {"image": "00329.nii.gz"}, {"image": "00330.nii.gz"}, {"image": "00331.nii.gz"}, {"image": "00332.nii.gz"}, {"image": "00333.nii.gz"}, {"image": "00334.nii.gz"}, {"image": "00335.nii.gz"}, {"image": "00336.nii.gz"}, {"image": "00337.nii.gz"}, {"image": "00338.nii.gz"}, {"image": "00339.nii.gz"}, {"image": "00340.nii.gz"}, {"image": "00341.nii.gz"}, {"image": "00342.nii.gz"}, {"image": "00343.nii.gz"}, {"image": "00344.nii.gz"}, {"image": "00345.nii.gz"}, {"image": "00346.nii.gz"}, {"image": "00347.nii.gz"}, {"image": "00348.nii.gz"}, {"image": "00349.nii.gz"}, {"image": "00350.nii.gz"}, {"image": "00351.nii.gz"}, {"image": "00352.nii.gz"}, {"image": "00353.nii.gz"}, {"image": "00354.nii.gz"}, {"image": "00355.nii.gz"}, {"image": "00356.nii.gz"}, {"image": "00357.nii.gz"}, {"image": "00358.nii.gz"}, {"image": "00359.nii.gz"}, {"image": "00360.nii.gz"}, {"image": "00361.nii.gz"}, {"image": "00362.nii.gz"}, {"image": "00363.nii.gz"}, {"image": "00364.nii.gz"}, {"image": "00365.nii.gz"}, {"image": "00366.nii.gz"}, {"image": "00367.nii.gz"}, {"image": "00368.nii.gz"}, {"image": "00369.nii.gz"}, {"image": "00370.nii.gz"}, {"image": "00371.nii.gz"}, {"image": "00372.nii.gz"}, {"image": "00373.nii.gz"}, {"image": "00374.nii.gz"}, {"image": "00375.nii.gz"}, {"image": "00376.nii.gz"}, {"image": "00377.nii.gz"}, {"image": "00378.nii.gz"}, {"image": "00379.nii.gz"}, {"image": "00380.nii.gz"}, {"image": "00381.nii.gz"}, {"image": "00382.nii.gz"}, {"image": "00383.nii.gz"}, {"image": "00384.nii.gz"}, {"image": "00385.nii.gz"}, {"image": "00386.nii.gz"}, {"image": "00387.nii.gz"}, {"image": "00388.nii.gz"}, {"image": "00389.nii.gz"}, {"image": "00390.nii.gz"}, {"image": "00391.nii.gz"}, {"image": "00392.nii.gz"}, {"image": "00393.nii.gz"}, {"image": "00394.nii.gz"}, {"image": "00395.nii.gz"}, {"image": "00396.nii.gz"}, {"image": "00397.nii.gz"}, {"image": "00398.nii.gz"}, {"image": "00399.nii.gz"}, {"image": "00400.nii.gz"}, {"image": "00401.nii.gz"}, {"image": "00402.nii.gz"}, {"image": "00403.nii.gz"}, {"image": "00404.nii.gz"}, {"image": "00405.nii.gz"}, {"image": "00406.nii.gz"}, {"image": "00407.nii.gz"}, {"image": "00408.nii.gz"}, {"image": "00409.nii.gz"}, {"image": "00410.nii.gz"}, {"image": "00411.nii.gz"}, {"image": "00412.nii.gz"}, {"image": "00413.nii.gz"}, {"image": "00414.nii.gz"}, {"image": "00415.nii.gz"}, {"image": "00416.nii.gz"}, {"image": "00417.nii.gz"}, {"image": "00418.nii.gz"}, {"image": "00419.nii.gz"}, {"image": "00420.nii.gz"}, {"image": "00421.nii.gz"}, {"image": "00422.nii.gz"}, {"image": "00423.nii.gz"}, {"image": "00424.nii.gz"}, {"image": "00425.nii.gz"}, {"image": "00426.nii.gz"}, {"image": "00427.nii.gz"}, {"image": "00428.nii.gz"}, {"image": "00429.nii.gz"}, {"image": "00430.nii.gz"}, {"image": "00431.nii.gz"}, {"image": "00432.nii.gz"}, {"image": "00433.nii.gz"}, {"image": "00434.nii.gz"}, {"image": "00435.nii.gz"}, {"image": "00436.nii.gz"}, {"image": "00437.nii.gz"}, {"image": "00438.nii.gz"}, {"image": "00439.nii.gz"}, {"image": "00440.nii.gz"}, {"image": "00441.nii.gz"}, {"image": "00442.nii.gz"}, {"image": "00443.nii.gz"}, {"image": "00444.nii.gz"}, {"image": "00445.nii.gz"}, {"image": "00446.nii.gz"}, {"image": "00447.nii.gz"}, {"image": "00448.nii.gz"}, {"image": "00449.nii.gz"}, {"image": "00450.nii.gz"}, {"image": "00451.nii.gz"}, {"image": "00452.nii.gz"}, {"image": "00453.nii.gz"}, {"image": "00454.nii.gz"}, {"image": "00455.nii.gz"}, {"image": "00456.nii.gz"}, {"image": "00457.nii.gz"}, {"image": "00458.nii.gz"}, {"image": "00459.nii.gz"}, {"image": "00460.nii.gz"}, {"image": "00461.nii.gz"}, {"image": "00462.nii.gz"}, {"image": "00463.nii.gz"}, {"image": "00464.nii.gz"}, {"image": "00465.nii.gz"}, {"image": "00466.nii.gz"}, {"image": "00467.nii.gz"}, {"image": "00468.nii.gz"}, {"image": "00469.nii.gz"}, {"image": "00470.nii.gz"}, {"image": "00471.nii.gz"}, {"image": "00472.nii.gz"}, {"image": "00473.nii.gz"}, {"image": "00474.nii.gz"}, {"image": "00475.nii.gz"}, {"image": "00476.nii.gz"}, {"image": "00477.nii.gz"}, {"image": "00478.nii.gz"}, {"image": "00479.nii.gz"}, {"image": "00480.nii.gz"}, {"image": "00481.nii.gz"}, {"image": "00482.nii.gz"}, {"image": "00483.nii.gz"}, {"image": "00484.nii.gz"}, {"image": "00485.nii.gz"}, {"image": "00486.nii.gz"}, {"image": "00487.nii.gz"}, {"image": "00488.nii.gz"}, {"image": "00489.nii.gz"}, {"image": "00490.nii.gz"}, {"image": "00491.nii.gz"}, {"image": "00492.nii.gz"}, {"image": "00493.nii.gz"}, {"image": "00494.nii.gz"}, {"image": "00495.nii.gz"}, {"image": "00496.nii.gz"}, {"image": "00497.nii.gz"}, {"image": "00498.nii.gz"}, {"image": "00499.nii.gz"}, {"image": "00500.nii.gz"}, {"image": "00501.nii.gz"}, {"image": "00502.nii.gz"}, {"image": "00503.nii.gz"}, {"image": "00504.nii.gz"}, {"image": "00505.nii.gz"}, {"image": "00506.nii.gz"}, {"image": "00507.nii.gz"}, {"image": "00508.nii.gz"}, {"image": "00509.nii.gz"}, {"image": "00510.nii.gz"}, {"image": "00511.nii.gz"}, {"image": "00512.nii.gz"}, {"image": "00513.nii.gz"}, {"image": "00514.nii.gz"}, {"image": "00515.nii.gz"}, {"image": "00516.nii.gz"}, {"image": "00517.nii.gz"}, {"image": "00518.nii.gz"}, {"image": "00519.nii.gz"}, {"image": "00520.nii.gz"}, {"image": "00521.nii.gz"}, {"image": "00522.nii.gz"}, {"image": "00523.nii.gz"}, {"image": "00524.nii.gz"}, {"image": "00525.nii.gz"}, {"image": "00526.nii.gz"}, {"image": "00527.nii.gz"}, {"image": "00528.nii.gz"}, {"image": "00529.nii.gz"}, {"image": "00530.nii.gz"}, {"image": "00531.nii.gz"}, {"image": "00532.nii.gz"}, {"image": "00533.nii.gz"}, {"image": "00534.nii.gz"}, {"image": "00535.nii.gz"}, {"image": "00536.nii.gz"}, {"image": "00537.nii.gz"}, {"image": "00538.nii.gz"}, {"image": "00539.nii.gz"}, {"image": "00540.nii.gz"}, {"image": "00541.nii.gz"}, {"image": "00542.nii.gz"}, {"image": "00543.nii.gz"}, {"image": "00544.nii.gz"}, {"image": "00545.nii.gz"}, {"image": "00546.nii.gz"}, {"image": "00547.nii.gz"}, {"image": "00548.nii.gz"}, {"image": "00549.nii.gz"}, {"image": "00550.nii.gz"}, {"image": "00551.nii.gz"}, {"image": "00552.nii.gz"}, {"image": "00553.nii.gz"}, {"image": "00554.nii.gz"}, {"image": "00555.nii.gz"}, {"image": "00556.nii.gz"}, {"image": "00557.nii.gz"}, {"image": "00558.nii.gz"}, {"image": "00559.nii.gz"}, {"image": "00560.nii.gz"}, {"image": "00561.nii.gz"}, {"image": "00562.nii.gz"}, {"image": "00563.nii.gz"}, {"image": "00564.nii.gz"}, {"image": "00565.nii.gz"}, {"image": "00566.nii.gz"}, {"image": "00567.nii.gz"}, {"image": "00568.nii.gz"}, {"image": "00569.nii.gz"}, {"image": "00570.nii.gz"}, {"image": "00571.nii.gz"}, {"image": "00572.nii.gz"}, {"image": "00573.nii.gz"}, {"image": "00574.nii.gz"}, {"image": "00575.nii.gz"}, {"image": "00576.nii.gz"}, {"image": "00577.nii.gz"}, {"image": "00578.nii.gz"}, {"image": "00579.nii.gz"}, {"image": "00580.nii.gz"}, {"image": "00581.nii.gz"}, {"image": "00582.nii.gz"}, {"image": "00583.nii.gz"}, {"image": "00584.nii.gz"}, {"image": "00585.nii.gz"}, {"image": "00586.nii.gz"}, {"image": "00587.nii.gz"}, {"image": "00588.nii.gz"}, {"image": "00589.nii.gz"}, {"image": "00590.nii.gz"}, {"image": "00591.nii.gz"}, {"image": "00592.nii.gz"}, {"image": "00593.nii.gz"}, {"image": "00594.nii.gz"}, {"image": "00595.nii.gz"}, {"image": "00596.nii.gz"}, {"image": "00597.nii.gz"}, {"image": "00598.nii.gz"}, {"image": "00599.nii.gz"}, {"image": "00600.nii.gz"}, {"image": "00601.nii.gz"}, {"image": "00602.nii.gz"}, {"image": "00603.nii.gz"}, {"image": "00604.nii.gz"}, {"image": "00605.nii.gz"}], "createDate": "2023-07-10_18-24-15"}